brutifus/__init__.py
brutifus/__main__.py
brutifus/brutifus.py
brutifus/brutifus_cof.py
brutifus/brutifus_metadata.py
brutifus/brutifus_plots.py
brutifus/brutifus_red.py
brutifus/brutifus_tools.py
brutifus/brutifus_version.py
brutifus/brutifus_wcs.py
brutifus/exec_scripts/brutifus_execute.py
brutifus/exec_scripts/brutifus_params.py
brutifus/exec_scripts/params_brutifus.yaml
brutifus/exec_scripts/procsteps_brutifus.yaml
brutifus/mpl_styles/brutifus_plots.mplstyle
brutifus/mpl_styles/brutifus_plots_nolatex.mplstyle
brutifus-2019.8.3.dist-info/LICENSE
brutifus-2019.8.3.dist-info/METADATA
brutifus-2019.8.3.dist-info/WHEEL
brutifus-2019.8.3.dist-info/entry_points.txt
brutifus-2019.8.3.dist-info/top_level.txt
brutifus-2019.8.3.dist-info/RECORD
