Metadata-Version: 2.1
Name: brutifus
Version: 2019.8.3
Summary: Python module to process IFU datacubes.
Home-page: http://fpavogt.github.io/brutifus/
Author: F.P.A. Vogt
Author-email: frederic.vogt@alumni.anu.edu.au
License: GNU General Public License
Download-URL: https://github.com/fpavogt/brutifus/archive/master.zip
Platform: UNKNOWN
Classifier: Development Status :: 3 - Alpha
Classifier: Intended Audience :: Science/Research
Classifier: Topic :: Scientific/Engineering :: Astronomy
Classifier: License :: OSI Approved :: GNU General Public License v3 or later (GPLv3+)
Classifier: Programming Language :: Python :: 3.7
Requires-Python: >=3
Requires-Dist: numpy (>=1.14.2)
Requires-Dist: scipy (>=1.1.0)
Requires-Dist: matplotlib (>=3.0.0)
Requires-Dist: astropy (>=3.0)
Requires-Dist: astroquery (>=0.3.4)
Requires-Dist: statsmodels (>=0.9.0)
Requires-Dist: photutils (>=0.6)
Requires-Dist: PyYAML (>=5.1)
